revit_extract/RevitExtractor.py
revit_extract/__init__.py
test/__init__.py
test/test_revit_extractor.py
revit_extractor-0.1.2.dist-info/METADATA
revit_extractor-0.1.2.dist-info/WHEEL
revit_extractor-0.1.2.dist-info/top_level.txt
revit_extractor-0.1.2.dist-info/RECORD
