Metadata-Version: 2.1
Name: revit-extractor
Version: 0.1.2
Summary: A Library allow extract revit without open revit
Author: chuongmep
Author-email: chuongpqvn@gmail.com
Requires-Python: >=3.9
Requires-Dist: aps-toolkit
Requires-Dist: olefile
